Img2UrlApi/ImgUploader.py
Img2UrlApi/__init__.py
Img2UrlApi-0.2.dist-info/METADATA
Img2UrlApi-0.2.dist-info/WHEEL
Img2UrlApi-0.2.dist-info/top_level.txt
Img2UrlApi-0.2.dist-info/RECORD
